{
  "parent": "minecraft:recipes/root",
  "criteria": {
    "has_crops_garlic": {
      "conditions": {
        "items": [
          {
            "tag": "c:crops/garlic"
          }
        ]
      },
      "trigger": "minecraft:inventory_changed"
    },
    "has_crops_onion": {
      "conditions": {
        "items": [
          {
            "tag": "c:crops/onion"
          }
        ]
      },
      "trigger": "minecraft:inventory_changed"
    },
    "has_fish_sauce_bottle": {
      "conditions": {
        "items": [
          {
            "items": [
              "ubesdelight:fish_sauce_bottle"
            ]
          }
        ]
      },
      "trigger": "minecraft:inventory_changed"
    },
    "has_foods_raw_meats_raw_chicken": {
      "conditions": {
        "items": [
          {
            "tag": "c:foods/raw_meats/raw_chicken"
          }
        ]
      },
      "trigger": "minecraft:inventory_changed"
    },
    "has_foods_raw_meats_raw_pork": {
      "conditions": {
        "items": [
          {
            "tag": "c:foods/raw_meats/raw_pork"
          }
        ]
      },
      "trigger": "minecraft:inventory_changed"
    },
    "has_the_recipe": {
      "conditions": {
        "recipe": "ubesdelight:farmersdelight/cooking/sisig_from_cooking_pot"
      },
      "trigger": "minecraft:recipe_unlocked"
    }
  },
  "requirements": [
    [
      "has_foods_raw_meats_raw_pork",
      "has_foods_raw_meats_raw_chicken",
      "has_crops_onion",
      "has_crops_garlic",
      "has_fish_sauce_bottle",
      "has_the_recipe"
    ]
  ],
  "rewards": {
    "recipes": [
      "ubesdelight:farmersdelight/cooking/sisig_from_cooking_pot"
    ]
  },
  "sends_telemetry_event": false
}