{
  "type": "ubesdelight:baking_mat",
  "ingredients": [
    {
      "item": "minecraft:egg"
    },
    {
      "tag": "c:tea_ingredients/sweet/weak"
    },
    {
      "tag": "c:tea_ingredients/sweet/weak"
    },
    {
      "tag": "c:foods/milk"
    },
    {
      "tag": "c:crops/ube"
    },
    {
      "tag": "c:foods/milk"
    },
    {
      "tag": "c:foods/milk"
    },
    {
      "item": "minecraft:wheat"
    },
    {
      "item": "minecraft:wheat"
    }
  ],
  "processing_stages": [],
  "result": [
    {
      "item": {
        "count": 1,
        "id": "ubesdelight:ube_cake"
      }
    },
    {
      "chance": 0.5,
      "item": {
        "count": 1,
        "id": "ubesdelight:ube_cake"
      }
    }
  ],
  "tool": {
    "tag": "c:tools/rolling_pin"
  }
}